<!--
    API Monitor Definitions
    (c) 2010-2011, Rohitab Batra <rohitab@rohitab.com>
    http://www.rohitab.com/apimonitor/
-->
<ApiMonitor>
    <Include Filename="Headers\windows.h.xml" />
    <Module Name="Storprop.dll" CallingConvention="STDCALL" ErrorFunc="GetLastError" OnlineHelp="MSDN">
        <!-- Device Management -->
        <Category Name="Devices/Device Management" />
        <Api Name="CdromDisableDigitalPlayback">
            <Param Type="HDEVINFO" Name="DevInfo" />
            <Param Type="PSP_DEVINFO_DATA" Name="DevInfoData" />
            <Return Type="LONG" />
            <Success Return="NotEqual" Value="0" />
        </Api>
        <Api Name="CdromEnableDigitalPlayback">
            <Param Type="HDEVINFO" Name="DevInfo" />
            <Param Type="PSP_DEVINFO_DATA" Name="DevInfoData" />
            <Param Type="BOOLEAN" Name="ForceUnknown" />
            <Return Type="LONG" />
            <Success Return="NotEqual" Value="0" />
        </Api>
        <Api Name="CdromIsDigitalPlaybackEnabled">
            <Param Type="HDEVINFO" Name="DevInfo" />
            <Param Type="PSP_DEVINFO_DATA" Name="DevInfoData" />
            <Param Type="PBOOLEAN" Name="Enabled" />
            <Return Type="LONG" />
            <Success Return="NotEqual" Value="0" />
        </Api>
        <Api Name="CdromKnownGoodDigitalPlayback">
            <Param Type="HDEVINFO" Name="DevInfo" />
            <Param Type="PSP_DEVINFO_DATA" Name="DevInfoData" />
            <Return Type="BOOL" />
            <Success Return="NotEqual" Value="0" />
        </Api>
        <Api Name="DvdLauncher">
            <Param Type="HWND" Name="HWnd" />
            <Param Type="CHAR" Name="DriveLetter" />
            <Return Type="BOOL" />
            <Success Return="NotEqual" Value="0" />
        </Api>
    </Module>
</ApiMonitor>