<!--
    API Monitor Definitions
    (c) 2011, Rohitab Batra <rohitab@rohitab.com>
    http://www.rohitab.com/apimonitor/
-->
<ApiMonitor>
    <Include Filename="Interfaces\WIC\WindowsCodecs.xml" />
    <Include Filename="Interfaces\IUnknown.xml" />
    <Interface Name="IWICBitmapLock" Id="{00000123-a8f2-4877-ba0a-fd2b6645fb94}" BaseInterface="IUnknown" OnlineHelp="MSDN" ErrorFunc="HRESULT" Category="Graphics and Multimedia/Windows Imaging Component">
        <!-- Methods -->
        <Api Name="GetSize">
            <Param Type="UINT*" Name="puiWidth" />
            <Param Type="UINT*" Name="puiHeight" />
            <Return Type="HRESULT" />
            <Success Return="Equal" Value="0" />
        </Api>
        <Api Name="GetStride">
            <Param Type="UINT*" Name="pcbStride" />
            <Return Type="HRESULT" />
            <Success Return="Equal" Value="0" />
        </Api>
        <Api Name="GetDataPointer">
            <Param Type="UINT*" Name="pcbBufferSize" />
            <Param Type="WICInProcPointer*" Name="ppbData" />
            <Return Type="HRESULT" />
            <Success Return="Equal" Value="0" />
        </Api>
        <Api Name="GetPixelFormat">
            <Param Type="WICPixelFormatGUID*" Name="pPixelFormat" />
            <Return Type="HRESULT" />
            <Success Return="Equal" Value="0" />
        </Api>
    </Interface>
</ApiMonitor>
